{
    "PBAEPDPNKEJ": 7210408,
    "KJNKFMPAGAA": [
        {
            "JOLEJEFDNJJ": 721040801,
            "CLMNEDLMAJL": [
                721040802,
                721040803
            ],
            "IFAOOKCBDGD": {
                "_type": "TALK_ROLE_NPC",
                "_id": "20300"
            },
            "EMKCOIBADBJ": 1371331546,
            "ODLPANKOAPL": "",
            "ANJMDLPMIEK": "",
            "KBIBLEDOMCP": "",
            "MKPDFLFNGDK": "",
            "GLGCPMKJFGC": "",
            "PGCBJDMIAKD": "",
            "FOIBHJHAFFP": ""
        },
        {
            "JOLEJEFDNJJ": 721040802,
            "NBOLDNEAEFO": "TALK_SHOW_FORCE_SELECT",
            "IFAOOKCBDGD": {
                "_type": "TALK_ROLE_PLAYER",
                "_id": ""
            },
            "EMKCOIBADBJ": 1309014538,
            "ODLPANKOAPL": "",
            "ANJMDLPMIEK": "",
            "KBIBLEDOMCP": "",
            "MKPDFLFNGDK": "",
            "GLGCPMKJFGC": "",
            "PGCBJDMIAKD": "UI/open_giving_page",
            "FOIBHJHAFFP": ""
        },
        {
            "JOLEJEFDNJJ": 721040803,
            "CLMNEDLMAJL": [
                721040804
            ],
            "NBOLDNEAEFO": "TALK_SHOW_FORCE_SELECT",
            "IFAOOKCBDGD": {
                "_type": "TALK_ROLE_PLAYER",
                "_id": ""
            },
            "EMKCOIBADBJ": 1258124658,
            "ODLPANKOAPL": "",
            "ANJMDLPMIEK": "",
            "KBIBLEDOMCP": "",
            "MKPDFLFNGDK": "",
            "GLGCPMKJFGC": "",
            "PGCBJDMIAKD": "",
            "FOIBHJHAFFP": ""
        },
        {
            "JOLEJEFDNJJ": 721040804,
            "IFAOOKCBDGD": {
                "_type": "TALK_ROLE_NPC",
                "_id": "20300"
            },
            "EMKCOIBADBJ": 400585842,
            "ODLPANKOAPL": "",
            "ANJMDLPMIEK": "",
            "KBIBLEDOMCP": "",
            "MKPDFLFNGDK": "",
            "GLGCPMKJFGC": "",
            "PGCBJDMIAKD": "",
            "FOIBHJHAFFP": ""
        }
    ]
}