{
    "BBMNINPKFAI": 2001203,
    "HDICBCEOELI": [
        {
            "PEDENGHCEAO": 200120301,
            "GAHHFHJMIMC": [
                200120302
            ],
            "CLCDJBPNOLH": {
                "type": "TALK_ROLE_NPC",
                "id": "157001"
            },
            "GFOBCFNGFGN": 884663769,
            "LPNMANCHFHM": "",
            "JALBFFBLPCF": "",
            "KKPLFPGJHMH": "",
            "INOEAGGCOIP": "",
            "FLMPENEHOFO": "",
            "EFPAMKIJEJG": "",
            "OEFBCGJFPEI": ""
        },
        {
            "PEDENGHCEAO": 200120302,
            "GAHHFHJMIMC": [
                200120303
            ],
            "CLCDJBPNOLH": {
                "type": "TALK_ROLE_NPC",
                "id": "157001"
            },
            "GFOBCFNGFGN": 4138690161,
            "LPNMANCHFHM": "",
            "JALBFFBLPCF": "",
            "KKPLFPGJHMH": "",
            "INOEAGGCOIP": "",
            "FLMPENEHOFO": "",
            "EFPAMKIJEJG": "",
            "OEFBCGJFPEI": ""
        },
        {
            "PEDENGHCEAO": 200120303,
            "GAHHFHJMIMC": [
                200120304
            ],
            "CLCDJBPNOLH": {
                "type": "TALK_ROLE_NPC",
                "id": "157001"
            },
            "GFOBCFNGFGN": 3962102113,
            "LPNMANCHFHM": "",
            "JALBFFBLPCF": "",
            "KKPLFPGJHMH": "",
            "INOEAGGCOIP": "",
            "FLMPENEHOFO": "",
            "EFPAMKIJEJG": "",
            "OEFBCGJFPEI": ""
        },
        {
            "PEDENGHCEAO": 200120304,
            "CLCDJBPNOLH": {
                "type": "TALK_ROLE_NPC",
                "id": "157001"
            },
            "GFOBCFNGFGN": 382442857,
            "LPNMANCHFHM": "",
            "JALBFFBLPCF": "",
            "KKPLFPGJHMH": "",
            "INOEAGGCOIP": "",
            "FLMPENEHOFO": "",
            "EFPAMKIJEJG": "",
            "OEFBCGJFPEI": ""
        }
    ]
}