{
    "talkId": 6904117,
    "type": "ACTIVITY",
    "dialogList": [
        {
            "id": 690411301,
            "talkRole": {
                "type": "TALK_ROLE_NPC",
                "id": "9041"
            },
            "talkContentTextMapHash": 2558484506,
            "talkAssetPath": "",
            "talkAssetPathAlter": "",
            "talkAudioName": "",
            "actionBefore": "",
            "actionWhile": "",
            "actionAfter": "",
            "optionIcon": ""
        }
    ]
}